HA_cfg_cleaner_DiosWolf/__init__.py
HA_cfg_cleaner_DiosWolf/main.py
HA_cfg_cleaner_DiosWolf/castom_errors/castom_errors.py
HA_cfg_cleaner_DiosWolf/configs_HA/config_HA.json
HA_cfg_cleaner_DiosWolf/configs_HA/config_HA_wind.json
HA_cfg_cleaner_DiosWolf/data_classes_json/args_parse.py
HA_cfg_cleaner_DiosWolf/data_classes_json/file_config.py
HA_cfg_cleaner_DiosWolf/data_classes_json/instructions.py
HA_cfg_cleaner_DiosWolf/files_editors/addons_editor.py
HA_cfg_cleaner_DiosWolf/files_editors/automations_editor.py
HA_cfg_cleaner_DiosWolf/files_editors/editor_restore_state.py
HA_cfg_cleaner_DiosWolf/files_editors/fileIO_cls.py
HA_cfg_cleaner_DiosWolf/files_editors/file_folder_editor_cls.py
HA_cfg_cleaner_DiosWolf/files_editors/find_in_files_cls.py
HA_cfg_cleaner_DiosWolf/files_editors/integrations_cls.py
HA_cfg_cleaner_DiosWolf/files_editors/script_editor_cls.py
HA_cfg_cleaner_DiosWolf/ha_requests/ha_request.py
HA_cfg_cleaner_DiosWolf/instruction_classes/instruction_executor.py
HA_cfg_cleaner_DiosWolf/parse_classes/arguments_parse.py
HA_cfg_cleaner_DiosWolf/parse_classes/parse_cls.py
build/lib/HA_cfg_cleaner_DiosWolf/__init__.py
build/lib/HA_cfg_cleaner_DiosWolf/main.py
build/lib/HA_cfg_cleaner_DiosWolf/castom_errors/castom_errors.py
build/lib/HA_cfg_cleaner_DiosWolf/data_classes_json/args_parse.py
build/lib/HA_cfg_cleaner_DiosWolf/data_classes_json/file_config.py
build/lib/HA_cfg_cleaner_DiosWolf/data_classes_json/instructions.py
build/lib/HA_cfg_cleaner_DiosWolf/files_editors/addons_editor.py
build/lib/HA_cfg_cleaner_DiosWolf/files_editors/automations_editor.py
build/lib/HA_cfg_cleaner_DiosWolf/files_editors/editor_restore_state.py
build/lib/HA_cfg_cleaner_DiosWolf/files_editors/fileIO_cls.py
build/lib/HA_cfg_cleaner_DiosWolf/files_editors/file_folder_editor_cls.py
build/lib/HA_cfg_cleaner_DiosWolf/files_editors/find_in_files_cls.py
build/lib/HA_cfg_cleaner_DiosWolf/files_editors/integrations_cls.py
build/lib/HA_cfg_cleaner_DiosWolf/files_editors/script_editor_cls.py
HA_cfg_cleaner_DiosWolf-0.0.75.dist-info/LICENSE
HA_cfg_cleaner_DiosWolf-0.0.75.dist-info/METADATA
HA_cfg_cleaner_DiosWolf-0.0.75.dist-info/WHEEL
HA_cfg_cleaner_DiosWolf-0.0.75.dist-info/entry_points.txt
HA_cfg_cleaner_DiosWolf-0.0.75.dist-info/top_level.txt
HA_cfg_cleaner_DiosWolf-0.0.75.dist-info/RECORD
