Metadata-Version: 2.1
Name: HA_cfg_cleaner_DiosWolf
Version: 0.0.75
License-File: LICENSE
Requires-Dist: ruamel.yaml==0.18.5
Requires-Dist: dacite==1.8.1
Requires-Dist: requests==2.31.0
Requires-Dist: setuptools==69.0.3
